lfreleng_test_python_project-0.0.1.dev0.dist-info/METADATA
lfreleng_test_python_project-0.0.1.dev0.dist-info/WHEEL
lfreleng_test_python_project-0.0.1.dev0.dist-info/entry_points.txt
lfreleng_test_python_project/__init__.py
lfreleng_test_python_project/cli.py
lfreleng_test_python_project/test.sh
lfreleng_test_python_project-0.0.1.dev0.dist-info/RECORD
