Metadata-Version: 2.1
Name: lfreleng-test-python-project
Version: 0.0.1.dev0
Summary: Sample Python project used for testing actions
Author-Email: Matthew Watkins <93649628+ModeSevenIndustrialSolutions@users.noreply.github.com>
License: Apache-2.0
Classifier: Intended Audience :: Developers
Classifier: Intended Audience :: Science/Research
Classifier: License :: OSI Approved :: Apache Software License
Classifier: Operating System :: MacOS
Classifier: Operating System :: Microsoft :: Windows
Classifier: Operating System :: Unix
Classifier: Programming Language :: Python
Classifier: Programming Language :: Python :: 3
Classifier: Programming Language :: Python :: 3 :: Only
Classifier: Programming Language :: Python :: 3.12
Classifier: Programming Language :: Python :: 3.11
Classifier: Topic :: Office/Business :: Financial
Classifier: Topic :: Scientific/Engineering
Classifier: Topic :: Software Development
Requires-Python: <3.13,>=3.11
Requires-Dist: typer>=0.15.2
Requires-Dist: jupyterlab>=4.3.6
